{"_type":"export","__export_format":4,"__export_date":"2023-07-21T12:07:20.588Z","__export_source":"insomnia.desktop.app:v2023.4.0","resources":[{"_id":"req_1fda9e0cb1b146d7b6caa1e619e3d8e6","parentId":"wrk_1a738f97391d436b85a7e1fce5fcbae5","modified":1688678792512,"created":1688308334228,"url":"{{ _.api }}/v1/healthcheck","name":"healthcheck","description":"","method":"GET","body":{},"parameters":[],"headers":[],"authentication":{},"metaSortKey":-1688389517404.375,"isPrivate":false,"settingStoreCookies":true,"settingSendCookies":true,"settingDisableRenderRequestBody":false,"settingEncodeUrl":true,"settingRebuildPath":true,"settingFollowRedirects":"global","_type":"request"},{"_id":"wrk_1a738f97391d436b85a7e1fce5fcbae5","parentId":null,"modified":1688308331442,"created":1688308331442,"name":"truenorth","description":"","scope":"collection","_type":"workspace"},{"_id":"req_fc4526ef45bc41248e4e29e90cd2450d","parentId":"wrk_1a738f97391d436b85a7e1fce5fcbae5","modified":1688678798514,"created":1688674373257,"url":"{{ _.api }}/v1/docs","name":"docs","description":"","method":"GET","body":{},"parameters":[],"headers":[],"authentication":{},"metaSortKey":-1688386617334.2188,"isPrivate":false,"settingStoreCookies":true,"settingSendCookies":true,"settingDisableRenderRequestBody":false,"settingEncodeUrl":true,"settingRebuildPath":true,"settingFollowRedirects":"global","_type":"request"},{"_id":"req_b18b58983a8143beaa56792451859c29","parentId":"fld_28e9e15569de4bb1bfb251a048d4a1e4","modified":1688678802923,"created":1688311391373,"url":"{{ _.api }}/v1/account/auth","name":"auth","description":"","method":"POST","body":{"mimeType":"application/json","text":"{\n\t\"username\": \"albo\",\n\t\"password\": \"123456\"\n}"},"parameters":[],"headers":[{"name":"Content-Type","value":"application/json"}],"authentication":{},"metaSortKey":-1688354716537.5,"isPrivate":false,"settingStoreCookies":true,"settingSendCookies":true,"settingDisableRenderRequestBody":false,"settingEncodeUrl":true,"settingRebuildPath":true,"settingFollowRedirects":"global","_type":"request"},{"_id":"fld_28e9e15569de4bb1bfb251a048d4a1e4","parentId":"wrk_1a738f97391d436b85a7e1fce5fcbae5","modified":1688674368537,"created":1688401098897,"name":"account","description":"","environment":{},"environmentPropertyOrder":null,"metaSortKey":-1688383717264.0625,"_type":"request_group"},{"_id":"req_6615ae094dcc40308e22fc2c35d421bd","parentId":"fld_28e9e15569de4bb1bfb251a048d4a1e4","modified":1688678806885,"created":1688311560554,"url":"{{ _.api }}/v1/account/register","name":"register","description":"","method":"POST","body":{"mimeType":"application/json","text":"{\n\t\"username\": \"albo\",\n\t\"password\": \"123456\"\n}"},"parameters":[],"headers":[{"name":"Content-Type","value":"application/json"}],"authentication":{},"metaSortKey":-1688354716487.5,"isPrivate":false,"settingStoreCookies":true,"settingSendCookies":true,"settingDisableRenderRequestBody":false,"settingEncodeUrl":true,"settingRebuildPath":true,"settingFollowRedirects":"global","_type":"request"},{"_id":"req_ea151436129f45b0a575a9e96c8d42ed","parentId":"fld_28e9e15569de4bb1bfb251a048d4a1e4","modified":1688678812086,"created":1688311589338,"url":"{{ _.api }}/v1/account","name":"enable/disable account","description":"","method":"PUT","body":{"mimeType":"application/json","text":"{\n\t\"enable\": true\n}"},"parameters":[],"headers":[{"name":"Content-Type","value":"application/json","id":"pair_86604ba8eb6f456c809d57fee0474e2d"},{"id":"pair_228b33d78e1f4e059912d562d08ce9c5","name":"Authorization","value":"{% response 'body', 'req_b18b58983a8143beaa56792451859c29', 'b64::JC50b2tlbg==::46b', 'never', 60 %}","description":""}],"authentication":{},"metaSortKey":-1688354716437.5,"isPrivate":false,"settingStoreCookies":true,"settingSendCookies":true,"settingDisableRenderRequestBody":false,"settingEncodeUrl":true,"settingRebuildPath":true,"settingFollowRedirects":"global","_type":"request"},{"_id":"req_69583869e09547d994db73c493f01afa","parentId":"fld_e03a032af5074bf8bdb7f8641adf1a1a","modified":1688678815993,"created":1688311571497,"url":"{{ _.api }}/v1/wallet","name":"add credit balance","description":"","method":"POST","body":{"mimeType":"application/json","text":"{\n\t\"credits\": 10\n}"},"parameters":[],"headers":[{"name":"Content-Type","value":"application/json","id":"pair_efa8daae2dee4752b3f7c61bc299f169"},{"id":"pair_94346de2216a410a8d50c1057a9f58b6","name":"Authorization","value":"Bearer {% response 'body', 'req_b18b58983a8143beaa56792451859c29', 'b64::JC50b2tlbg==::46b', 'never', 60 %}","description":""}],"authentication":{},"metaSortKey":-1688120475488.6562,"isPrivate":false,"settingStoreCookies":true,"settingSendCookies":true,"settingDisableRenderRequestBody":false,"settingEncodeUrl":true,"settingRebuildPath":true,"settingFollowRedirects":"global","_type":"request"},{"_id":"fld_e03a032af5074bf8bdb7f8641adf1a1a","parentId":"wrk_1a738f97391d436b85a7e1fce5fcbae5","modified":1688401173657,"created":1688401136473,"name":"wallet","description":"","environment":{},"environmentPropertyOrder":null,"metaSortKey":-1688377917123.75,"_type":"request_group"},{"_id":"req_b9e730c3921f463bbb0a92da7cf1c926","parentId":"fld_e03a032af5074bf8bdb7f8641adf1a1a","modified":1688678820365,"created":1688313226801,"url":"{{ _.api }}/v1/wallet","name":"get credit balance","description":"","method":"GET","body":{"mimeType":"application/json","text":""},"parameters":[],"headers":[{"name":"Content-Type","value":"application/json","id":"pair_7c25d2581cd54048bfc083f5c3f53aeb"},{"id":"pair_0b204ecfc3ef4f468f6eeb56366d81ea","name":"Authorization","value":"Bearer {% response 'body', 'req_b18b58983a8143beaa56792451859c29', 'b64::JC50b2tlbg==::46b', 'never', 60 %}","description":""}],"authentication":{},"metaSortKey":-1688120475438.6562,"isPrivate":false,"settingStoreCookies":true,"settingSendCookies":true,"settingDisableRenderRequestBody":false,"settingEncodeUrl":true,"settingRebuildPath":true,"settingFollowRedirects":"global","_type":"request"},{"_id":"req_20bfa481227a4a50809876fa03f1bded","parentId":"fld_fe0d7307182b47b0a49be939d24a47c9","modified":1688678827116,"created":1688395526342,"url":"{{ _.api }}/v1/calculator/operations","name":"get operators","description":"","method":"GET","body":{"mimeType":"application/json","text":""},"parameters":[],"headers":[{"name":"Content-Type","value":"application/json","id":"pair_bd21d3cf2efa454982fb5f9756b72a04"},{"id":"pair_a8d212e458c846ec9d703b3f4508e6a0","name":"Authorization","value":"Bearer {% response 'body', 'req_b18b58983a8143beaa56792451859c29', 'b64::JC50b2tlbg==::46b', 'never', 60 %}","description":""}],"authentication":{},"metaSortKey":-1688092436870.8438,"isPrivate":false,"settingStoreCookies":true,"settingSendCookies":true,"settingDisableRenderRequestBody":false,"settingEncodeUrl":true,"settingRebuildPath":true,"settingFollowRedirects":"global","_type":"request"},{"_id":"fld_fe0d7307182b47b0a49be939d24a47c9","parentId":"wrk_1a738f97391d436b85a7e1fce5fcbae5","modified":1688402958303,"created":1688401155301,"name":"calculator","description":"","environment":{},"environmentPropertyOrder":null,"metaSortKey":-1688354716562.5,"_type":"request_group"},{"_id":"req_cf1a0dcf5729490c8d6099939966ff3f","parentId":"fld_fe0d7307182b47b0a49be939d24a47c9","modified":1688739856345,"created":1688311697792,"url":"{{ _.api }}/v1/calculator","name":"execute formula","description":"","method":"POST","body":{"mimeType":"application/json","text":"{\n\t\"formula\": \"4 + 2 * 3 / √16\"\n}"},"parameters":[],"headers":[{"name":"Content-Type","value":"application/json","id":"pair_df6199ebc9b542c29b762e804d82080b"},{"id":"pair_771614dd91aa4ea1a14a308c870630ca","name":"Authorization","value":"Bearer {% response 'body', 'req_b18b58983a8143beaa56792451859c29', 'b64::JC50b2tlbg==::46b', 'never', 60 %}","description":""}],"authentication":{},"metaSortKey":-1688092436820.8438,"isPrivate":false,"settingStoreCookies":true,"settingSendCookies":true,"settingDisableRenderRequestBody":false,"settingEncodeUrl":true,"settingRebuildPath":true,"settingFollowRedirects":"global","_type":"request"},{"_id":"req_0882f0b8eda5489288ddcef926ba722d","parentId":"fld_7e4c0c55944f48a9bc72b5a078813e87","modified":1688678837728,"created":1688479788571,"url":"{{ _.api }}/v1/random-string","name":"random string","description":"","method":"POST","body":{"mimeType":"application/json","text":"{\n\t\"length\": 10\n}"},"parameters":[],"headers":[{"name":"Content-Type","value":"application/json","id":"pair_df6199ebc9b542c29b762e804d82080b"},{"id":"pair_771614dd91aa4ea1a14a308c870630ca","name":"Authorization","value":"Bearer {% response 'body', 'req_b18b58983a8143beaa56792451859c29', 'b64::JC50b2tlbg==::46b', 'never', 60 %}","description":""}],"authentication":{},"metaSortKey":-1688440434424,"isPrivate":false,"settingStoreCookies":true,"settingSendCookies":true,"settingDisableRenderRequestBody":false,"settingEncodeUrl":true,"settingRebuildPath":true,"settingFollowRedirects":"global","_type":"request"},{"_id":"fld_7e4c0c55944f48a9bc72b5a078813e87","parentId":"wrk_1a738f97391d436b85a7e1fce5fcbae5","modified":1688479766671,"created":1688479751263,"name":"random string","description":"","environment":{},"environmentPropertyOrder":null,"metaSortKey":-1688331525395.25,"_type":"request_group"},{"_id":"req_06f07197df224e39bcc3b0e80b5f43bf","parentId":"fld_f7f086400d574886bc535fee0cb22bc7","modified":1688732514292,"created":1688410348178,"url":"{{ _.api }}/v1/record","name":"get records","description":"","method":"GET","body":{"mimeType":"application/json","text":""},"parameters":[{"id":"pair_fd44b2d7ed5143d7a2af4f62afab0f65","name":"page","value":"1","description":"","disabled":false},{"id":"pair_9cc34bcee1df4f218a788dc72afe13b3","name":"limit","value":"10","description":"","disabled":false},{"id":"pair_4f832fb22af548c2bc022d910898e8e6","name":"sort","value":"id=desc","description":"","disabled":false},{"id":"pair_6c3675eba0f7429ebc59a69a9f629527","name":"search","value":"operation=Addition|id=26","description":"","disabled":true},{"id":"pair_4559e836928447b98d96cda0d60b2b99","name":"search","value":"operation%Add|formula%Test","description":"","disabled":true}],"headers":[{"name":"Content-Type","value":"application/json","id":"pair_bd21d3cf2efa454982fb5f9756b72a04"},{"id":"pair_a8d212e458c846ec9d703b3f4508e6a0","name":"Authorization","value":"Bearer {% response 'body', 'req_b18b58983a8143beaa56792451859c29', 'b64::JC50b2tlbg==::46b', 'never', 60 %}","description":""}],"authentication":{},"metaSortKey":-1688092436870.8438,"isPrivate":false,"settingStoreCookies":true,"settingSendCookies":true,"settingDisableRenderRequestBody":false,"settingEncodeUrl":true,"settingRebuildPath":true,"settingFollowRedirects":"global","_type":"request"},{"_id":"fld_f7f086400d574886bc535fee0cb22bc7","parentId":"wrk_1a738f97391d436b85a7e1fce5fcbae5","modified":1688654417066,"created":1688410348169,"name":"records","description":"","environment":{},"environmentPropertyOrder":null,"metaSortKey":-1688253033299.1875,"_type":"request_group"},{"_id":"req_7ae0f56fc0f14da48b2f5f9f388ab890","parentId":"fld_f7f086400d574886bc535fee0cb22bc7","modified":1688678853259,"created":1688647432985,"url":"{{ _.api }}/v1/record/26","name":"delete records","description":"","method":"DELETE","body":{"mimeType":"application/json","text":""},"parameters":[],"headers":[{"name":"Content-Type","value":"application/json","id":"pair_bd21d3cf2efa454982fb5f9756b72a04"},{"id":"pair_a8d212e458c846ec9d703b3f4508e6a0","name":"Authorization","value":"Bearer {% response 'body', 'req_b18b58983a8143beaa56792451859c29', 'b64::JC50b2tlbg==::46b', 'never', 60 %}","description":""}],"authentication":{},"metaSortKey":-1688092436845.8438,"isPrivate":false,"settingStoreCookies":true,"settingSendCookies":true,"settingDisableRenderRequestBody":false,"settingEncodeUrl":true,"settingRebuildPath":true,"settingFollowRedirects":"global","_type":"request"},{"_id":"req_34d0632aaa3744efb013ead64fe768e8","parentId":"fld_49005d4fa8374f958bf0f46e2b117e1a","modified":1688678859225,"created":1688654423238,"url":"{{ _.api }}/v1/report","name":"get report","description":"","method":"GET","body":{"mimeType":"application/json","text":""},"parameters":[{"id":"pair_fd44b2d7ed5143d7a2af4f62afab0f65","name":"page","value":"1","description":"","disabled":true},{"id":"pair_9cc34bcee1df4f218a788dc72afe13b3","name":"limit","value":"10","description":"","disabled":true},{"id":"pair_4f832fb22af548c2bc022d910898e8e6","name":"sort","value":"id=desc","description":"","disabled":true},{"id":"pair_6c3675eba0f7429ebc59a69a9f629527","name":"search","value":"operation=Addition|id=26","description":"","disabled":true}],"headers":[{"name":"Content-Type","value":"application/json","id":"pair_bd21d3cf2efa454982fb5f9756b72a04"},{"id":"pair_a8d212e458c846ec9d703b3f4508e6a0","name":"Authorization","value":"Bearer {% response 'body', 'req_b18b58983a8143beaa56792451859c29', 'b64::JC50b2tlbg==::46b', 'never', 60 %}","description":""}],"authentication":{},"metaSortKey":-1688092436858.3438,"isPrivate":false,"settingStoreCookies":true,"settingSendCookies":true,"settingDisableRenderRequestBody":false,"settingEncodeUrl":true,"settingRebuildPath":true,"settingFollowRedirects":"global","_type":"request"},{"_id":"fld_49005d4fa8374f958bf0f46e2b117e1a","parentId":"wrk_1a738f97391d436b85a7e1fce5fcbae5","modified":1688654414340,"created":1688654393070,"name":"reports","description":"","environment":{},"environmentPropertyOrder":null,"metaSortKey":-1688197732370.375,"_type":"request_group"},{"_id":"env_f51a64fe782563c0ef1561bee4ae4611556b3b73","parentId":"wrk_1a738f97391d436b85a7e1fce5fcbae5","modified":1688308331451,"created":1688308331451,"name":"Base Environment","data":{},"dataPropertyOrder":null,"color":null,"isPrivate":false,"metaSortKey":1688308331451,"_type":"environment"},{"_id":"jar_f51a64fe782563c0ef1561bee4ae4611556b3b73","parentId":"wrk_1a738f97391d436b85a7e1fce5fcbae5","modified":1688479499630,"created":1688308331453,"name":"Default Jar","cookies":[{"key":"__cflb","value":"02DiuEMAZFhhWAbaKrF1fuSZexDk78uezsL8QbNK5ZVR5","expires":"2023-07-11T13:51:46.000Z","domain":"www.random.org","path":"/","httpOnly":true,"extensions":["SameSite=Lax"],"hostOnly":true,"creation":"2023-07-04T13:51:47.468Z","lastAccessed":"2023-07-04T13:51:47.468Z","id":"6070235792942629"},{"key":"RDOSESSION","value":"ems03ennc2ongma2g2uinm3a32","expires":"2023-07-05T13:51:47.000Z","maxAge":86400,"domain":"random.org","path":"/","secure":true,"hostOnly":false,"creation":"2023-07-04T13:51:47.470Z","lastAccessed":"2023-07-04T13:51:47.470Z","id":"15621318972872578"},{"key":"__cflb","value":"02DiuEMAZFhhWAbaKrF1fuSZexDk78ueya3jCy3o2U4KV","expires":"2023-07-11T14:04:59.000Z","domain":"api.random.org","path":"/","httpOnly":true,"extensions":["SameSite=Lax"],"hostOnly":true,"creation":"2023-07-04T14:04:59.629Z","lastAccessed":"2023-07-04T14:04:59.629Z","id":"8890798534313342"}],"_type":"cookie_jar"},{"_id":"env_c5b058b43f9849cc9eab2534da5fc943","parentId":"env_f51a64fe782563c0ef1561bee4ae4611556b3b73","modified":1688678753584,"created":1688678727907,"name":"local","data":{"api":"http://localhost:4000"},"dataPropertyOrder":{"&":["api"]},"color":null,"isPrivate":false,"metaSortKey":1688678727908,"_type":"environment"},{"_id":"env_7ad1d91a9eba42afb0f64a5d5d15df0a","parentId":"env_f51a64fe782563c0ef1561bee4ae4611556b3b73","modified":1689803229597,"created":1688678755013,"name":"prod","data":{"api":"http://ec2-44-204-72-27.compute-1.amazonaws.com:4000"},"dataPropertyOrder":{"&":["api"]},"color":null,"isPrivate":false,"metaSortKey":1688678755013,"_type":"environment"}]}